vlac/__init__.py
vlac/vlac.py
Vectors_of_Locally_Aggregate_Concepts-0.1.dist-info/LICENSE
Vectors_of_Locally_Aggregate_Concepts-0.1.dist-info/METADATA
Vectors_of_Locally_Aggregate_Concepts-0.1.dist-info/WHEEL
Vectors_of_Locally_Aggregate_Concepts-0.1.dist-info/top_level.txt
Vectors_of_Locally_Aggregate_Concepts-0.1.dist-info/RECORD
